django_json_logging/__init__.py
django_json_logging/_stub_settings.py
django_json_logging/context.py
django_json_logging/logging.py
django_json_logging/middleware.py
django_json_logging-0.0.7.dist-info/WHEEL
django_json_logging-0.0.7.dist-info/METADATA
django_json_logging-0.0.7.dist-info/RECORD
