Metadata-Version: 2.1
Name: django_json_logging
Version: 0.0.7
Summary: Various JSON logging extensions for the Django Framework
Home-page: https://github.com/vskrachkov/django_json_logging
Author: Vicheslav Krachkov
Author-email: vskrachkov@gmail.com
Requires-Python: >=3.8
Requires-Dist: django>=2.2
Requires-Dist: json-log-formatter>=0.3.1, <=0.4.0
